{
  "timestamp": "2026-07-08 08:15:05",
  "venues": {
    "BADI-1": {
      "currentfill": "44",
      "freespace": 156,
      "maxspace": 200,
      "temperatureWater": "25.2",
      "openClosed": "offen"
    },
    "flb6939": {
      "currentfill": "3",
      "freespace": 997,
      "maxspace": 1000,
      "temperatureWater": "24",
      "openClosed": "geschlossen"
    },
    "fb012": {
      "currentfill": "5",
      "freespace": 2595,
      "maxspace": 2600,
      "temperatureWater": "24",
      "openClosed": "geschlossen"
    },
    "SSD-6": {
      "currentfill": "25",
      "freespace": 55,
      "maxspace": 80,
      "temperatureWater": null,
      "openClosed": null
    },
    "SSD-3": {
      "currentfill": "28",
      "freespace": 0,
      "maxspace": 28,
      "temperatureWater": null,
      "openClosed": null
    },
    "SSD-5": {
      "currentfill": "10",
      "freespace": 60,
      "maxspace": 70,
      "temperatureWater": null,
      "openClosed": null
    },
    "SSD-10": {
      "currentfill": "211",
      "freespace": 589,
      "maxspace": 800,
      "temperatureWater": "24",
      "openClosed": "offen"
    },
    "seb6948": {
      "currentfill": "5",
      "freespace": 695,
      "maxspace": 700,
      "temperatureWater": "25",
      "openClosed": "geschlossen"
    },
    "flb8803": {
      "currentfill": "2",
      "freespace": 798,
      "maxspace": 800,
      "temperatureWater": "24",
      "openClosed": "geschlossen"
    },
    "SSD-7": {
      "currentfill": "38",
      "freespace": 162,
      "maxspace": 200,
      "temperatureWater": null,
      "openClosed": null
    },
    "SSD-2": {
      "currentfill": "20",
      "freespace": 50,
      "maxspace": 70,
      "temperatureWater": null,
      "openClosed": null
    },
    "seb6946": {
      "currentfill": "47",
      "freespace": 4453,
      "maxspace": 4500,
      "temperatureWater": "25",
      "openClosed": "offen"
    },
    "seb6947": {
      "currentfill": "0",
      "freespace": 3500,
      "maxspace": 3500,
      "temperatureWater": "25",
      "openClosed": "geschlossen"
    },
    "flb6940": {
      "currentfill": "0",
      "freespace": 800,
      "maxspace": 800,
      "temperatureWater": "24",
      "openClosed": "geschlossen"
    },
    "fb008": {
      "currentfill": "0",
      "freespace": 2001,
      "maxspace": 2001,
      "temperatureWater": "25",
      "openClosed": "geschlossen"
    },
    "SSD-4": {
      "currentfill": "0",
      "freespace": 220,
      "maxspace": 220,
      "temperatureWater": null,
      "openClosed": null
    },
    "SSD-8": {
      "currentfill": "0",
      "freespace": 200,
      "maxspace": 200,
      "temperatureWater": null,
      "openClosed": null
    },
    "LETZI-1": {
      "currentfill": "167",
      "freespace": 3633,
      "maxspace": 3800,
      "temperatureWater": "25",
      "openClosed": "offen"
    },
    "SSD-11": {
      "currentfill": "81",
      "freespace": 1919,
      "maxspace": 2000,
      "temperatureWater": "24",
      "openClosed": "offen"
    },
    "flb6941": {
      "currentfill": "33",
      "freespace": 317,
      "maxspace": 350,
      "temperatureWater": "25",
      "openClosed": "offen"
    },
    "fb018": {
      "currentfill": "2",
      "freespace": 2998,
      "maxspace": 3000,
      "temperatureWater": "24",
      "openClosed": "geschlossen"
    },
    "fb006": {
      "currentfill": "0",
      "freespace": 7500,
      "maxspace": 7500,
      "temperatureWater": "28",
      "openClosed": "geschlossen"
    },
    "flb6938": {
      "currentfill": null,
      "freespace": null,
      "maxspace": null,
      "temperatureWater": "33",
      "openClosed": "geschlossen"
    },
    "flb6942": {
      "currentfill": null,
      "freespace": null,
      "maxspace": null,
      "temperatureWater": "25",
      "openClosed": "geschlossen"
    }
  }
}