{
  "timestamp": "2026-07-18 13:00:04",
  "venues": {
    "flb6941": {
      "currentfill": "158",
      "freespace": 192,
      "maxspace": 350,
      "temperatureWater": "25",
      "openClosed": "offen"
    },
    "SSD-3": {
      "currentfill": "0",
      "freespace": 28,
      "maxspace": 28,
      "temperatureWater": null,
      "openClosed": null
    },
    "SSD-6": {
      "currentfill": "0",
      "freespace": 80,
      "maxspace": 80,
      "temperatureWater": null,
      "openClosed": null
    },
    "SSD-2": {
      "currentfill": "10",
      "freespace": 60,
      "maxspace": 70,
      "temperatureWater": null,
      "openClosed": null
    },
    "SSD-10": {
      "currentfill": "403",
      "freespace": 397,
      "maxspace": 800,
      "temperatureWater": "25",
      "openClosed": "offen"
    },
    "seb6947": {
      "currentfill": "683",
      "freespace": 2817,
      "maxspace": 3500,
      "temperatureWater": "26",
      "openClosed": "offen"
    },
    "SSD-7": {
      "currentfill": "51",
      "freespace": 149,
      "maxspace": 200,
      "temperatureWater": null,
      "openClosed": null
    },
    "fb006": {
      "currentfill": "346",
      "freespace": 7154,
      "maxspace": 7500,
      "temperatureWater": "26",
      "openClosed": "offen"
    },
    "SSD-11": {
      "currentfill": "185",
      "freespace": 1815,
      "maxspace": 2000,
      "temperatureWater": "25",
      "openClosed": "offen"
    },
    "seb6948": {
      "currentfill": "161",
      "freespace": 539,
      "maxspace": 700,
      "temperatureWater": "27",
      "openClosed": "offen"
    },
    "fb012": {
      "currentfill": "352",
      "freespace": 2248,
      "maxspace": 2600,
      "temperatureWater": "24.5",
      "openClosed": "offen"
    },
    "fb008": {
      "currentfill": "120",
      "freespace": 1881,
      "maxspace": 2001,
      "temperatureWater": "25",
      "openClosed": "offen"
    },
    "SSD-4": {
      "currentfill": "0",
      "freespace": 220,
      "maxspace": 220,
      "temperatureWater": null,
      "openClosed": null
    },
    "seb6946": {
      "currentfill": "835",
      "freespace": 3665,
      "maxspace": 4500,
      "temperatureWater": "27",
      "openClosed": "offen"
    },
    "fb018": {
      "currentfill": "151",
      "freespace": 2849,
      "maxspace": 3000,
      "temperatureWater": "25",
      "openClosed": "offen"
    },
    "flb8803": {
      "currentfill": "176",
      "freespace": 624,
      "maxspace": 800,
      "temperatureWater": "25",
      "openClosed": "offen"
    },
    "flb6939": {
      "currentfill": "403",
      "freespace": 597,
      "maxspace": 1000,
      "temperatureWater": "25",
      "openClosed": "offen"
    },
    "BADI-1": {
      "currentfill": "274",
      "freespace": -74,
      "maxspace": 200,
      "temperatureWater": "26.4",
      "openClosed": "offen"
    },
    "LETZI-1": {
      "currentfill": "414",
      "freespace": 3386,
      "maxspace": 3800,
      "temperatureWater": "24.6",
      "openClosed": "offen"
    },
    "flb6940": {
      "currentfill": "208",
      "freespace": 592,
      "maxspace": 800,
      "temperatureWater": "24",
      "openClosed": "offen"
    },
    "SSD-5": {
      "currentfill": "0",
      "freespace": 70,
      "maxspace": 70,
      "temperatureWater": null,
      "openClosed": null
    },
    "flb6938": {
      "currentfill": null,
      "freespace": null,
      "maxspace": null,
      "temperatureWater": "25",
      "openClosed": "offen"
    },
    "flb6942": {
      "currentfill": null,
      "freespace": null,
      "maxspace": null,
      "temperatureWater": "26",
      "openClosed": "offen"
    },
    "DOLDER-1": {
      "currentfill": null,
      "freespace": null,
      "maxspace": null,
      "temperatureWater": "24",
      "openClosed": "offen"
    }
  }
}