{
  "timestamp": "2026-07-08 12:44:15",
  "venues": {
    "SSD-3": {
      "currentfill": "8",
      "freespace": 20,
      "maxspace": 28,
      "temperatureWater": null,
      "openClosed": null
    },
    "fb018": {
      "currentfill": "213",
      "freespace": 2787,
      "maxspace": 3000,
      "temperatureWater": "24",
      "openClosed": "offen"
    },
    "BADI-1": {
      "currentfill": "250",
      "freespace": -50,
      "maxspace": 200,
      "temperatureWater": "25.2",
      "openClosed": "offen"
    },
    "fb012": {
      "currentfill": "421",
      "freespace": 2179,
      "maxspace": 2600,
      "temperatureWater": "23",
      "openClosed": "offen"
    },
    "SSD-5": {
      "currentfill": "12",
      "freespace": 58,
      "maxspace": 70,
      "temperatureWater": null,
      "openClosed": null
    },
    "seb6948": {
      "currentfill": "70",
      "freespace": 630,
      "maxspace": 700,
      "temperatureWater": "25",
      "openClosed": "offen"
    },
    "SSD-4": {
      "currentfill": "3",
      "freespace": 217,
      "maxspace": 220,
      "temperatureWater": null,
      "openClosed": null
    },
    "flb6940": {
      "currentfill": "169",
      "freespace": 631,
      "maxspace": 800,
      "temperatureWater": "24",
      "openClosed": "offen"
    },
    "fb006": {
      "currentfill": "299",
      "freespace": 7201,
      "maxspace": 7500,
      "temperatureWater": "25",
      "openClosed": "offen"
    },
    "flb6941": {
      "currentfill": "185",
      "freespace": 165,
      "maxspace": 350,
      "temperatureWater": "25",
      "openClosed": "offen"
    },
    "SSD-8": {
      "currentfill": "0",
      "freespace": 200,
      "maxspace": 200,
      "temperatureWater": null,
      "openClosed": null
    },
    "SSD-6": {
      "currentfill": "21",
      "freespace": 59,
      "maxspace": 80,
      "temperatureWater": null,
      "openClosed": null
    },
    "SSD-2": {
      "currentfill": "4",
      "freespace": 66,
      "maxspace": 70,
      "temperatureWater": null,
      "openClosed": null
    },
    "SSD-10": {
      "currentfill": "261",
      "freespace": 539,
      "maxspace": 800,
      "temperatureWater": "24",
      "openClosed": "offen"
    },
    "seb6947": {
      "currentfill": "353",
      "freespace": 3147,
      "maxspace": 3500,
      "temperatureWater": "25",
      "openClosed": "offen"
    },
    "flb8803": {
      "currentfill": "116",
      "freespace": 684,
      "maxspace": 800,
      "temperatureWater": "24",
      "openClosed": "offen"
    },
    "SSD-7": {
      "currentfill": "44",
      "freespace": 156,
      "maxspace": 200,
      "temperatureWater": null,
      "openClosed": null
    },
    "flb6939": {
      "currentfill": "300",
      "freespace": 700,
      "maxspace": 1000,
      "temperatureWater": "24",
      "openClosed": "offen"
    },
    "SSD-11": {
      "currentfill": "122",
      "freespace": 1878,
      "maxspace": 2000,
      "temperatureWater": "24",
      "openClosed": "offen"
    },
    "seb6946": {
      "currentfill": "428",
      "freespace": 4072,
      "maxspace": 4500,
      "temperatureWater": "25",
      "openClosed": "offen"
    },
    "LETZI-1": {
      "currentfill": "367",
      "freespace": 3433,
      "maxspace": 3800,
      "temperatureWater": "25",
      "openClosed": "offen"
    },
    "fb008": {
      "currentfill": "143",
      "freespace": 1858,
      "maxspace": 2001,
      "temperatureWater": "24",
      "openClosed": "offen"
    },
    "flb6938": {
      "currentfill": null,
      "freespace": null,
      "maxspace": null,
      "temperatureWater": "25",
      "openClosed": "offen"
    },
    "flb6942": {
      "currentfill": null,
      "freespace": null,
      "maxspace": null,
      "temperatureWater": "22",
      "openClosed": "offen"
    }
  }
}