{
  "timestamp": "2026-07-09 13:14:21",
  "venues": {
    "seb6947": {
      "currentfill": "1016",
      "freespace": 2484,
      "maxspace": 3500,
      "temperatureWater": "25",
      "openClosed": "offen"
    },
    "fb006": {
      "currentfill": "610",
      "freespace": 6890,
      "maxspace": 7500,
      "temperatureWater": "27",
      "openClosed": "offen"
    },
    "flb6940": {
      "currentfill": "197",
      "freespace": 603,
      "maxspace": 800,
      "temperatureWater": "23",
      "openClosed": "offen"
    },
    "SSD-3": {
      "currentfill": "14",
      "freespace": 14,
      "maxspace": 28,
      "temperatureWater": null,
      "openClosed": null
    },
    "seb6946": {
      "currentfill": "864",
      "freespace": 3636,
      "maxspace": 4500,
      "temperatureWater": "25",
      "openClosed": "offen"
    },
    "fb008": {
      "currentfill": "261",
      "freespace": 1740,
      "maxspace": 2001,
      "temperatureWater": "25",
      "openClosed": "offen"
    },
    "BADI-1": {
      "currentfill": "279",
      "freespace": -79,
      "maxspace": 200,
      "temperatureWater": "24.5",
      "openClosed": "offen"
    },
    "SSD-6": {
      "currentfill": "19",
      "freespace": 61,
      "maxspace": 80,
      "temperatureWater": null,
      "openClosed": null
    },
    "flb6941": {
      "currentfill": "249",
      "freespace": 101,
      "maxspace": 350,
      "temperatureWater": "24",
      "openClosed": "offen"
    },
    "seb6948": {
      "currentfill": "234",
      "freespace": 466,
      "maxspace": 700,
      "temperatureWater": "26",
      "openClosed": "offen"
    },
    "SSD-11": {
      "currentfill": "247",
      "freespace": 1753,
      "maxspace": 2000,
      "temperatureWater": "25",
      "openClosed": "offen"
    },
    "SSD-7": {
      "currentfill": "35",
      "freespace": 165,
      "maxspace": 200,
      "temperatureWater": null,
      "openClosed": null
    },
    "SSD-2": {
      "currentfill": "11",
      "freespace": 59,
      "maxspace": 70,
      "temperatureWater": null,
      "openClosed": null
    },
    "SSD-10": {
      "currentfill": "380",
      "freespace": 420,
      "maxspace": 800,
      "temperatureWater": "24",
      "openClosed": "offen"
    },
    "SSD-8": {
      "currentfill": "1",
      "freespace": 199,
      "maxspace": 200,
      "temperatureWater": null,
      "openClosed": null
    },
    "fb018": {
      "currentfill": "259",
      "freespace": 2741,
      "maxspace": 3000,
      "temperatureWater": "23",
      "openClosed": "offen"
    },
    "flb6939": {
      "currentfill": "319",
      "freespace": 681,
      "maxspace": 1000,
      "temperatureWater": "25",
      "openClosed": "offen"
    },
    "flb8803": {
      "currentfill": "199",
      "freespace": 601,
      "maxspace": 800,
      "temperatureWater": "25",
      "openClosed": "offen"
    },
    "fb012": {
      "currentfill": "706",
      "freespace": 1894,
      "maxspace": 2600,
      "temperatureWater": "24",
      "openClosed": "offen"
    },
    "SSD-5": {
      "currentfill": "12",
      "freespace": 58,
      "maxspace": 70,
      "temperatureWater": null,
      "openClosed": null
    },
    "SSD-4": {
      "currentfill": "2",
      "freespace": 218,
      "maxspace": 220,
      "temperatureWater": null,
      "openClosed": null
    },
    "LETZI-1": {
      "currentfill": "848",
      "freespace": 2952,
      "maxspace": 3800,
      "temperatureWater": "25",
      "openClosed": "offen"
    },
    "flb6938": {
      "currentfill": null,
      "freespace": null,
      "maxspace": null,
      "temperatureWater": "25",
      "openClosed": "offen"
    },
    "flb6942": {
      "currentfill": null,
      "freespace": null,
      "maxspace": null,
      "temperatureWater": "26",
      "openClosed": "offen"
    }
  }
}