{
  "timestamp": "2026-07-14 18:29:17",
  "venues": {
    "SSD-5": {
      "currentfill": "0",
      "freespace": 70,
      "maxspace": 70,
      "temperatureWater": null,
      "openClosed": null
    },
    "SSD-7": {
      "currentfill": "142",
      "freespace": 58,
      "maxspace": 200,
      "temperatureWater": null,
      "openClosed": null
    },
    "SSD-6": {
      "currentfill": "23",
      "freespace": 57,
      "maxspace": 80,
      "temperatureWater": null,
      "openClosed": null
    },
    "SSD-10": {
      "currentfill": "191",
      "freespace": 609,
      "maxspace": 800,
      "temperatureWater": "25",
      "openClosed": "offen"
    },
    "SSD-4": {
      "currentfill": "2",
      "freespace": 218,
      "maxspace": 220,
      "temperatureWater": null,
      "openClosed": null
    },
    "flb6941": {
      "currentfill": "73",
      "freespace": 277,
      "maxspace": 350,
      "temperatureWater": "26",
      "openClosed": "offen"
    },
    "SSD-11": {
      "currentfill": "139",
      "freespace": 1861,
      "maxspace": 2000,
      "temperatureWater": "25",
      "openClosed": "offen"
    },
    "fb018": {
      "currentfill": "149",
      "freespace": 2851,
      "maxspace": 3000,
      "temperatureWater": "24",
      "openClosed": "offen"
    },
    "LETZI-1": {
      "currentfill": "182",
      "freespace": 3618,
      "maxspace": 3800,
      "temperatureWater": "25",
      "openClosed": "offen"
    },
    "seb6946": {
      "currentfill": "93",
      "freespace": 4407,
      "maxspace": 4500,
      "temperatureWater": "26",
      "openClosed": "offen"
    },
    "fb012": {
      "currentfill": "147",
      "freespace": 2453,
      "maxspace": 2600,
      "temperatureWater": "25",
      "openClosed": "offen"
    },
    "SSD-3": {
      "currentfill": "1",
      "freespace": 27,
      "maxspace": 28,
      "temperatureWater": null,
      "openClosed": null
    },
    "flb6940": {
      "currentfill": "95",
      "freespace": 705,
      "maxspace": 800,
      "temperatureWater": "26",
      "openClosed": "offen"
    },
    "fb008": {
      "currentfill": "45",
      "freespace": 1956,
      "maxspace": 2001,
      "temperatureWater": "25",
      "openClosed": "offen"
    },
    "flb8803": {
      "currentfill": "225",
      "freespace": 575,
      "maxspace": 800,
      "temperatureWater": "25",
      "openClosed": "offen"
    },
    "flb6939": {
      "currentfill": "271",
      "freespace": 729,
      "maxspace": 1000,
      "temperatureWater": "26",
      "openClosed": "offen"
    },
    "seb6948": {
      "currentfill": "79",
      "freespace": 621,
      "maxspace": 700,
      "temperatureWater": "26",
      "openClosed": "offen"
    },
    "SSD-2": {
      "currentfill": "15",
      "freespace": 55,
      "maxspace": 70,
      "temperatureWater": null,
      "openClosed": null
    },
    "seb6947": {
      "currentfill": "84",
      "freespace": 3416,
      "maxspace": 3500,
      "temperatureWater": "26",
      "openClosed": "offen"
    },
    "BADI-1": {
      "currentfill": "145",
      "freespace": 55,
      "maxspace": 200,
      "temperatureWater": "26",
      "openClosed": "offen"
    },
    "fb006": {
      "currentfill": "222",
      "freespace": 7278,
      "maxspace": 7500,
      "temperatureWater": "25",
      "openClosed": "offen"
    },
    "flb6938": {
      "currentfill": null,
      "freespace": null,
      "maxspace": null,
      "temperatureWater": "25",
      "openClosed": "offen"
    },
    "flb6942": {
      "currentfill": null,
      "freespace": null,
      "maxspace": null,
      "temperatureWater": "26",
      "openClosed": "offen"
    },
    "DOLDER-1": {
      "currentfill": null,
      "freespace": null,
      "maxspace": null,
      "temperatureWater": "24",
      "openClosed": "offen"
    }
  }
}