{
  "timestamp": "2026-07-20 10:14:20",
  "venues": {
    "fb006": {
      "currentfill": "53",
      "freespace": 7447,
      "maxspace": 7500,
      "temperatureWater": "25",
      "openClosed": "offen"
    },
    "LETZI-1": {
      "currentfill": "82",
      "freespace": 3718,
      "maxspace": 3800,
      "temperatureWater": "24",
      "openClosed": "offen"
    },
    "seb6947": {
      "currentfill": "81",
      "freespace": 3419,
      "maxspace": 3500,
      "temperatureWater": "25",
      "openClosed": "offen"
    },
    "seb6946": {
      "currentfill": "106",
      "freespace": 4394,
      "maxspace": 4500,
      "temperatureWater": "26",
      "openClosed": "offen"
    },
    "BADI-1": {
      "currentfill": "48",
      "freespace": 152,
      "maxspace": 200,
      "temperatureWater": "26",
      "openClosed": "offen"
    },
    "SSD-3": {
      "currentfill": "1",
      "freespace": 27,
      "maxspace": 28,
      "temperatureWater": null,
      "openClosed": null
    },
    "flb8803": {
      "currentfill": "16",
      "freespace": 784,
      "maxspace": 800,
      "temperatureWater": "25",
      "openClosed": "offen"
    },
    "flb6941": {
      "currentfill": "41",
      "freespace": 309,
      "maxspace": 350,
      "temperatureWater": "24",
      "openClosed": "offen"
    },
    "SSD-2": {
      "currentfill": "0",
      "freespace": 70,
      "maxspace": 70,
      "temperatureWater": null,
      "openClosed": null
    },
    "flb6940": {
      "currentfill": "10",
      "freespace": 790,
      "maxspace": 800,
      "temperatureWater": "23",
      "openClosed": "offen"
    },
    "fb018": {
      "currentfill": "17",
      "freespace": 2983,
      "maxspace": 3000,
      "temperatureWater": "24",
      "openClosed": "offen"
    },
    "SSD-6": {
      "currentfill": "0",
      "freespace": 80,
      "maxspace": 80,
      "temperatureWater": null,
      "openClosed": null
    },
    "SSD-7": {
      "currentfill": "31",
      "freespace": 169,
      "maxspace": 200,
      "temperatureWater": null,
      "openClosed": null
    },
    "SSD-4": {
      "currentfill": "4",
      "freespace": 216,
      "maxspace": 220,
      "temperatureWater": null,
      "openClosed": null
    },
    "SSD-11": {
      "currentfill": "26",
      "freespace": 1974,
      "maxspace": 2000,
      "temperatureWater": "23",
      "openClosed": "offen"
    },
    "fb008": {
      "currentfill": "26",
      "freespace": 1975,
      "maxspace": 2001,
      "temperatureWater": "24",
      "openClosed": "offen"
    },
    "SSD-5": {
      "currentfill": "2",
      "freespace": 68,
      "maxspace": 70,
      "temperatureWater": null,
      "openClosed": null
    },
    "seb6948": {
      "currentfill": "23",
      "freespace": 677,
      "maxspace": 700,
      "temperatureWater": "26",
      "openClosed": "offen"
    },
    "fb012": {
      "currentfill": "60",
      "freespace": 2540,
      "maxspace": 2600,
      "temperatureWater": "23",
      "openClosed": "offen"
    },
    "SSD-10": {
      "currentfill": "93",
      "freespace": 707,
      "maxspace": 800,
      "temperatureWater": "24",
      "openClosed": "offen"
    },
    "flb6939": {
      "currentfill": "69",
      "freespace": 931,
      "maxspace": 1000,
      "temperatureWater": "25",
      "openClosed": "offen"
    },
    "flb6938": {
      "currentfill": null,
      "freespace": null,
      "maxspace": null,
      "temperatureWater": "25",
      "openClosed": "offen"
    },
    "flb6942": {
      "currentfill": null,
      "freespace": null,
      "maxspace": null,
      "temperatureWater": "26",
      "openClosed": "offen"
    },
    "DOLDER-1": {
      "currentfill": null,
      "freespace": null,
      "maxspace": null,
      "temperatureWater": "24",
      "openClosed": "geschlossen"
    }
  }
}