{
  "timestamp": "2026-07-06 10:00:04",
  "venues": {
    "fb008": {
      "currentfill": "227",
      "freespace": 1774,
      "maxspace": 2001,
      "temperatureWater": "25",
      "openClosed": "offen"
    },
    "fb006": {
      "currentfill": "393",
      "freespace": 7107,
      "maxspace": 7500,
      "temperatureWater": "26",
      "openClosed": "offen"
    },
    "SSD-6": {
      "currentfill": "25",
      "freespace": 55,
      "maxspace": 80,
      "temperatureWater": null,
      "openClosed": null
    },
    "SSD-2": {
      "currentfill": "43",
      "freespace": 27,
      "maxspace": 70,
      "temperatureWater": null,
      "openClosed": null
    },
    "SSD-4": {
      "currentfill": "0",
      "freespace": 220,
      "maxspace": 220,
      "temperatureWater": null,
      "openClosed": null
    },
    "BADI-1": {
      "currentfill": "98",
      "freespace": 102,
      "maxspace": 200,
      "temperatureWater": "25",
      "openClosed": "offen"
    },
    "SSD-5": {
      "currentfill": "0",
      "freespace": 70,
      "maxspace": 70,
      "temperatureWater": null,
      "openClosed": null
    },
    "flb6941": {
      "currentfill": "81",
      "freespace": 269,
      "maxspace": 350,
      "temperatureWater": "22",
      "openClosed": "offen"
    },
    "flb6939": {
      "currentfill": "123",
      "freespace": 877,
      "maxspace": 1000,
      "temperatureWater": "22",
      "openClosed": "offen"
    },
    "fb012": {
      "currentfill": "242",
      "freespace": 2358,
      "maxspace": 2600,
      "temperatureWater": "24",
      "openClosed": "offen"
    },
    "SSD-3": {
      "currentfill": "2",
      "freespace": 26,
      "maxspace": 28,
      "temperatureWater": null,
      "openClosed": null
    },
    "SSD-10": {
      "currentfill": "170",
      "freespace": 630,
      "maxspace": 800,
      "temperatureWater": "23",
      "openClosed": "offen"
    },
    "SSD-7": {
      "currentfill": "51",
      "freespace": 149,
      "maxspace": 200,
      "temperatureWater": null,
      "openClosed": null
    },
    "seb6947": {
      "currentfill": "256",
      "freespace": 3244,
      "maxspace": 3500,
      "temperatureWater": "25",
      "openClosed": "offen"
    },
    "SSD-11": {
      "currentfill": "127",
      "freespace": 1873,
      "maxspace": 2000,
      "temperatureWater": "24",
      "openClosed": "offen"
    },
    "seb6948": {
      "currentfill": "64",
      "freespace": 636,
      "maxspace": 700,
      "temperatureWater": "25",
      "openClosed": "offen"
    },
    "LETZI-1": {
      "currentfill": "232",
      "freespace": 3568,
      "maxspace": 3800,
      "temperatureWater": "25",
      "openClosed": "offen"
    },
    "flb8803": {
      "currentfill": "59",
      "freespace": 741,
      "maxspace": 800,
      "temperatureWater": "22",
      "openClosed": "offen"
    },
    "SSD-8": {
      "currentfill": "16",
      "freespace": 184,
      "maxspace": 200,
      "temperatureWater": null,
      "openClosed": null
    },
    "fb018": {
      "currentfill": "156",
      "freespace": 2844,
      "maxspace": 3000,
      "temperatureWater": "23",
      "openClosed": "offen"
    },
    "seb6946": {
      "currentfill": "259",
      "freespace": 4241,
      "maxspace": 4500,
      "temperatureWater": "25",
      "openClosed": "offen"
    },
    "flb6940": {
      "currentfill": "38",
      "freespace": 762,
      "maxspace": 800,
      "temperatureWater": "23",
      "openClosed": "offen"
    },
    "flb6938": {
      "currentfill": null,
      "freespace": null,
      "maxspace": null,
      "temperatureWater": "22",
      "openClosed": "offen"
    },
    "flb6942": {
      "currentfill": null,
      "freespace": null,
      "maxspace": null,
      "temperatureWater": "20",
      "openClosed": "offen"
    }
  }
}