{
  "timestamp": "2026-07-07 16:45:02",
  "venues": {
    "seb6948": {
      "currentfill": "131",
      "freespace": 569,
      "maxspace": 700,
      "temperatureWater": "25",
      "openClosed": "offen"
    },
    "LETZI-1": {
      "currentfill": "701",
      "freespace": 3099,
      "maxspace": 3800,
      "temperatureWater": "25",
      "openClosed": "offen"
    },
    "BADI-1": {
      "currentfill": "255",
      "freespace": -55,
      "maxspace": 200,
      "temperatureWater": "25",
      "openClosed": "offen"
    },
    "seb6947": {
      "currentfill": "912",
      "freespace": 2588,
      "maxspace": 3500,
      "temperatureWater": "25",
      "openClosed": "offen"
    },
    "flb6940": {
      "currentfill": "371",
      "freespace": 429,
      "maxspace": 800,
      "temperatureWater": "24",
      "openClosed": "offen"
    },
    "flb6941": {
      "currentfill": "250",
      "freespace": 100,
      "maxspace": 350,
      "temperatureWater": "23",
      "openClosed": "offen"
    },
    "fb008": {
      "currentfill": "265",
      "freespace": 1736,
      "maxspace": 2001,
      "temperatureWater": "25",
      "openClosed": "offen"
    },
    "fb012": {
      "currentfill": "657",
      "freespace": 1943,
      "maxspace": 2600,
      "temperatureWater": "24",
      "openClosed": "offen"
    },
    "SSD-11": {
      "currentfill": "258",
      "freespace": 1742,
      "maxspace": 2000,
      "temperatureWater": "25",
      "openClosed": "offen"
    },
    "flb8803": {
      "currentfill": "325",
      "freespace": 475,
      "maxspace": 800,
      "temperatureWater": "23",
      "openClosed": "offen"
    },
    "SSD-5": {
      "currentfill": "7",
      "freespace": 63,
      "maxspace": 70,
      "temperatureWater": null,
      "openClosed": null
    },
    "SSD-7": {
      "currentfill": "133",
      "freespace": 67,
      "maxspace": 200,
      "temperatureWater": null,
      "openClosed": null
    },
    "SSD-8": {
      "currentfill": "27",
      "freespace": 173,
      "maxspace": 200,
      "temperatureWater": null,
      "openClosed": null
    },
    "SSD-2": {
      "currentfill": "26",
      "freespace": 44,
      "maxspace": 70,
      "temperatureWater": null,
      "openClosed": null
    },
    "fb018": {
      "currentfill": "376",
      "freespace": 2624,
      "maxspace": 3000,
      "temperatureWater": "24",
      "openClosed": "offen"
    },
    "seb6946": {
      "currentfill": "770",
      "freespace": 3730,
      "maxspace": 4500,
      "temperatureWater": "25",
      "openClosed": "offen"
    },
    "SSD-4": {
      "currentfill": "1",
      "freespace": 219,
      "maxspace": 220,
      "temperatureWater": null,
      "openClosed": null
    },
    "flb6939": {
      "currentfill": "453",
      "freespace": 547,
      "maxspace": 1000,
      "temperatureWater": "23",
      "openClosed": "offen"
    },
    "SSD-6": {
      "currentfill": "36",
      "freespace": 44,
      "maxspace": 80,
      "temperatureWater": null,
      "openClosed": null
    },
    "SSD-3": {
      "currentfill": "15",
      "freespace": 13,
      "maxspace": 28,
      "temperatureWater": null,
      "openClosed": null
    },
    "fb006": {
      "currentfill": "673",
      "freespace": 6827,
      "maxspace": 7500,
      "temperatureWater": "26",
      "openClosed": "offen"
    },
    "SSD-10": {
      "currentfill": "414",
      "freespace": 386,
      "maxspace": 800,
      "temperatureWater": "24",
      "openClosed": "offen"
    },
    "flb6938": {
      "currentfill": null,
      "freespace": null,
      "maxspace": null,
      "temperatureWater": "23",
      "openClosed": "offen"
    },
    "flb6942": {
      "currentfill": null,
      "freespace": null,
      "maxspace": null,
      "temperatureWater": "25",
      "openClosed": "geschlossen"
    }
  }
}