{
  "timestamp": "2026-07-17 10:44:18",
  "venues": {
    "flb6939": {
      "currentfill": "99",
      "freespace": 901,
      "maxspace": 1000,
      "temperatureWater": "25",
      "openClosed": "offen"
    },
    "SSD-6": {
      "currentfill": "1",
      "freespace": 79,
      "maxspace": 80,
      "temperatureWater": null,
      "openClosed": null
    },
    "flb8803": {
      "currentfill": "47",
      "freespace": 753,
      "maxspace": 800,
      "temperatureWater": "26",
      "openClosed": "offen"
    },
    "fb006": {
      "currentfill": "130",
      "freespace": 7370,
      "maxspace": 7500,
      "temperatureWater": "25",
      "openClosed": "offen"
    },
    "flb6941": {
      "currentfill": "75",
      "freespace": 275,
      "maxspace": 350,
      "temperatureWater": "26",
      "openClosed": "offen"
    },
    "fb012": {
      "currentfill": "155",
      "freespace": 2445,
      "maxspace": 2600,
      "temperatureWater": "24",
      "openClosed": "offen"
    },
    "SSD-7": {
      "currentfill": "65",
      "freespace": 135,
      "maxspace": 200,
      "temperatureWater": null,
      "openClosed": null
    },
    "BADI-1": {
      "currentfill": "133",
      "freespace": 67,
      "maxspace": 200,
      "temperatureWater": "26.5",
      "openClosed": "offen"
    },
    "LETZI-1": {
      "currentfill": "148",
      "freespace": 3652,
      "maxspace": 3800,
      "temperatureWater": "25",
      "openClosed": "offen"
    },
    "SSD-11": {
      "currentfill": "29",
      "freespace": 1971,
      "maxspace": 2000,
      "temperatureWater": "25",
      "openClosed": "offen"
    },
    "SSD-4": {
      "currentfill": "1",
      "freespace": 219,
      "maxspace": 220,
      "temperatureWater": null,
      "openClosed": null
    },
    "SSD-2": {
      "currentfill": "8",
      "freespace": 62,
      "maxspace": 70,
      "temperatureWater": null,
      "openClosed": null
    },
    "seb6947": {
      "currentfill": "164",
      "freespace": 3336,
      "maxspace": 3500,
      "temperatureWater": "26",
      "openClosed": "offen"
    },
    "SSD-5": {
      "currentfill": "2",
      "freespace": 68,
      "maxspace": 70,
      "temperatureWater": null,
      "openClosed": null
    },
    "fb018": {
      "currentfill": "47",
      "freespace": 2953,
      "maxspace": 3000,
      "temperatureWater": "24",
      "openClosed": "offen"
    },
    "seb6948": {
      "currentfill": "56",
      "freespace": 644,
      "maxspace": 700,
      "temperatureWater": "27",
      "openClosed": "offen"
    },
    "SSD-3": {
      "currentfill": "1",
      "freespace": 27,
      "maxspace": 28,
      "temperatureWater": null,
      "openClosed": null
    },
    "flb6940": {
      "currentfill": "50",
      "freespace": 750,
      "maxspace": 800,
      "temperatureWater": "24",
      "openClosed": "offen"
    },
    "seb6946": {
      "currentfill": "174",
      "freespace": 4326,
      "maxspace": 4500,
      "temperatureWater": "27",
      "openClosed": "offen"
    },
    "SSD-10": {
      "currentfill": "146",
      "freespace": 654,
      "maxspace": 800,
      "temperatureWater": "25",
      "openClosed": "offen"
    },
    "fb008": {
      "currentfill": "63",
      "freespace": 1938,
      "maxspace": 2001,
      "temperatureWater": "25",
      "openClosed": "offen"
    },
    "flb6938": {
      "currentfill": null,
      "freespace": null,
      "maxspace": null,
      "temperatureWater": "25",
      "openClosed": "offen"
    },
    "flb6942": {
      "currentfill": null,
      "freespace": null,
      "maxspace": null,
      "temperatureWater": "26",
      "openClosed": "offen"
    },
    "DOLDER-1": {
      "currentfill": null,
      "freespace": null,
      "maxspace": null,
      "temperatureWater": "24",
      "openClosed": "offen"
    }
  }
}